odoo/addons/extendable_fastapi/README.rst
odoo/addons/extendable_fastapi/__init__.py
odoo/addons/extendable_fastapi/__manifest__.py
odoo/addons/extendable_fastapi/fastapi_dispatcher.py
odoo/addons/extendable_fastapi/schemas.py
odoo/addons/extendable_fastapi/i18n/extendable_fastapi.pot
odoo/addons/extendable_fastapi/i18n/it.po
odoo/addons/extendable_fastapi/models/__init__.py
odoo/addons/extendable_fastapi/models/fastapi_endpoint_demo.py
odoo/addons/extendable_fastapi/readme/CONTRIBUTORS.rst
odoo/addons/extendable_fastapi/readme/DESCRIPTION.rst
odoo/addons/extendable_fastapi/readme/HISTORY.rst
odoo/addons/extendable_fastapi/readme/newsfragments/.gitignore
odoo/addons/extendable_fastapi/static/description/icon.png
odoo/addons/extendable_fastapi/static/description/index.html
odoo/addons/extendable_fastapi/tests/__init__.py
odoo/addons/extendable_fastapi/tests/common.py
odoo/addons/extendable_fastapi/tests/routers.py
odoo/addons/extendable_fastapi/tests/schemas.py
odoo/addons/extendable_fastapi/tests/test_generic_extendable.py
odoo/addons/extendable_fastapi/tests/test_strict_extendable_base_model.py
odoo_addon_extendable_fastapi-16.0.2.1.2.dist-info/METADATA
odoo_addon_extendable_fastapi-16.0.2.1.2.dist-info/WHEEL
odoo_addon_extendable_fastapi-16.0.2.1.2.dist-info/top_level.txt
odoo_addon_extendable_fastapi-16.0.2.1.2.dist-info/RECORD
