Metadata-Version: 2.1
Name: odoo-addon-extendable_fastapi
Version: 16.0.2.1.2
Summary: Allows the use of extendable into fastapi apps
Home-page: https://github.com/OCA/rest-framework
Author: ACSONE SA/NV,Odoo Community Association (OCA)
Author-email: support@odoo-community.org
License: LGPL-3
Classifier: Programming Language :: Python
Classifier: Framework :: Odoo
Classifier: Framework :: Odoo :: 16.0
Classifier: License :: OSI Approved :: GNU Lesser General Public License v3 (LGPLv3)
Requires-Python: >=3.10
Requires-Dist: extendable-pydantic>=1.2.0
Requires-Dist: odoo-addon-extendable<16.1dev,>=16.0dev
Requires-Dist: odoo-addon-fastapi<16.1dev,>=16.0dev
Requires-Dist: odoo<16.1dev,>=16.0a
Requires-Dist: pydantic>=2.0.0
